app_namespace/__init__.py
app_namespace/loader.py
app_namespace/demo/__init__.py
app_namespace/demo/settings.py
app_namespace/demo/urls.py
app_namespace/demo/application/__init__.py
app_namespace/demo/application/templates/application/template.html
app_namespace/demo/application_appconfig/__init__.py
app_namespace/demo/application_appconfig/apps.py
app_namespace/demo/application_appconfig/templates/application/template.html
app_namespace/demo/application_extension/__init__.py
app_namespace/demo/application_extension/templates/application/template.html
app_namespace/demo/templates/application/template.html
app_namespace/tests/__init__.py
app_namespace/tests/settings.py
app_namespace/tests/tests.py
app_namespace/tests/urls.py
django_app_namespace_template_loader-0.4.1.dist-info/DESCRIPTION.rst
django_app_namespace_template_loader-0.4.1.dist-info/METADATA
django_app_namespace_template_loader-0.4.1.dist-info/RECORD
django_app_namespace_template_loader-0.4.1.dist-info/WHEEL
django_app_namespace_template_loader-0.4.1.dist-info/metadata.json
django_app_namespace_template_loader-0.4.1.dist-info/top_level.txt
