Metadata-Version: 2.0
Name: django-app-namespace-template-loader
Version: 0.4.1
Summary: Template loader allowing you to both extend and override a template at the same time. 
Home-page: https://github.com/Fantomas42/django-app-namespace-template-loader
Author: Fantomas42
Author-email: fantomas42@gmail.com
License: BSD License
Keywords: django,template,loader
Platform: any
Classifier: Framework :: Django
Classifier: Environment :: Web Environment
Classifier: Programming Language :: Python :: 2.7
Classifier: Programming Language :: Python :: 3.3
Classifier: Programming Language :: Python :: 3.4
Classifier: Intended Audience :: Developers
Classifier: Operating System :: OS Independent
Classifier: License :: OSI Approved :: BSD License
Classifier: Topic :: Software Development :: Libraries :: Python Modules
Requires-Dist: six
